{"version": 0.6, "generator": "Overpass API 0.7.62.5 1bd436f1", "osm3s": {"timestamp_osm_base": "2025-05-20T02:18:54Z", "copyright": "The data included in this document is from www.openstreetmap.org. The data is made available under ODbL."}, "elements": [{"type": "node", "id": 6185873629, "lat": 25.188889, "lon": 121.5741112}, {"type": "node", "id": 6185873630, "lat": 25.1887822, "lon": 121.5741676}, {"type": "node", "id": 6185873631, "lat": 25.1887337, "lon": 121.5740553}, {"type": "node", "id": 6185873632, "lat": 25.1888405, "lon": 121.5739989}, {"type": "node", "id": 6185873633, "lat": 25.1887734, "lon": 121.5754128}, {"type": "node", "id": 6185873634, "lat": 25.1886545, "lon": 121.5753162}, {"type": "node", "id": 6185873635, "lat": 25.1887385, "lon": 121.5751898}, {"type": "node", "id": 6185873636, "lat": 25.1888574, "lon": 121.5752864}, {"type": "way", "id": 660702636, "nodes": [6185873632, 6185873629, 6185873630, 6185873631, 6185873632], "tags": {"building": "yes"}}, {"type": "way", "id": 660702637, "nodes": [6185873636, 6185873633, 6185873634, 6185873635, 6185873636], "tags": {"building": "yes"}}]}