{"version": 0.6, "generator": "Overpass API 0.7.62.5 1bd436f1", "osm3s": {"timestamp_osm_base": "2025-05-27T11:16:01Z", "copyright": "The data included in this document is from www.openstreetmap.org. The data is made available under ODbL."}, "elements": [{"type": "node", "id": 9535983848, "lat": 23.1755681, "lon": 120.5647959}, {"type": "node", "id": 9535983849, "lat": 23.1756227, "lon": 120.5649205}, {"type": "node", "id": 9535983850, "lat": 23.1755383, "lon": 120.5649643}, {"type": "node", "id": 9535983852, "lat": 23.1755079, "lon": 120.5648271}, {"type": "node", "id": 11759326031, "lat": 23.1755415, "lon": 120.5649038}, {"type": "node", "id": 11759326032, "lat": 23.1755173, "lon": 120.5649163}, {"type": "way", "id": 1035229440, "nodes": [9535983848, 9535983849, 9535983850, 11759326032, 11759326031, 9535983852, 9535983848], "tags": {"building": "roof", "layer": "1"}}]}