{"version": 0.6, "generator": "Overpass API 0.7.62.5 1bd436f1", "osm3s": {"timestamp_osm_base": "2025-05-21T10:43:26Z", "copyright": "The data included in this document is from www.openstreetmap.org. The data is made available under ODbL."}, "elements": [{"type": "node", "id": 9528865672, "lat": 23.0293661, "lon": 120.5041397}, {"type": "node", "id": 9528865673, "lat": 23.0293491, "lon": 120.5041516}, {"type": "node", "id": 9528865674, "lat": 23.0293263, "lon": 120.5041136}, {"type": "node", "id": 9528865675, "lat": 23.0293448, "lon": 120.504102}, {"type": "node", "id": 9528865676, "lat": 23.0291719, "lon": 120.5039221}, {"type": "node", "id": 9528865677, "lat": 23.0291548, "lon": 120.5039484}, {"type": "node", "id": 9528865678, "lat": 23.0291307, "lon": 120.5039243}, {"type": "node", "id": 9528865679, "lat": 23.0291498, "lon": 120.5039003}, {"type": "way", "id": 1034368040, "nodes": [9528865672, 9528865673, 9528865674, 9528865675, 9528865672], "tags": {"amenity": "place_of_worship", "building": "yes", "name": "\u798f\u5fb7\u7960"}}, {"type": "way", "id": 1034368041, "nodes": [9528865676, 9528865677, 9528865678, 9528865679, 9528865676], "tags": {"amenity": "shelter", "building": "yes"}}]}